asyncio_guard/__init__.py
asyncio_guard/py.typed
asyncio_guard-1.0.0.dist-info/AUTHORS
asyncio_guard-1.0.0.dist-info/LICENSE
asyncio_guard-1.0.0.dist-info/METADATA
asyncio_guard-1.0.0.dist-info/WHEEL
asyncio_guard-1.0.0.dist-info/top_level.txt
asyncio_guard-1.0.0.dist-info/RECORD
