Metadata-Version: 2.1
Name: asyncio-guard
Version: 1.0.0
Summary: Guard that provide exclusive access to an object
Home-page: https://github.com/inyutin/asyncio_guard
Author: Dmitry Inyutin
Author-email: inyutin.da@gmail.com
License: MIT
Keywords: python asyncio mutex lock guard
Platform: any
Classifier: Programming Language :: Python :: 3
Classifier: License :: OSI Approved :: MIT License
Classifier: Operating System :: OS Independent
Requires-Python: >=3.7
License-File: LICENSE
License-File: AUTHORS
